deeptrain/__init__.py
deeptrain/callbacks.py
deeptrain/data_generator.py
deeptrain/introspection.py
deeptrain/metrics.py
deeptrain/preprocessing.py
deeptrain/train_generator.py
deeptrain/visuals.py
deeptrain/backend/__init__.py
deeptrain/backend/model_utils.py
deeptrain/backend/tensor_utils.py
deeptrain/util/__init__.py
deeptrain/util/_backend.py
deeptrain/util/_default_configs.py
deeptrain/util/_traingen_utils.py
deeptrain/util/algorithms.py
deeptrain/util/configs.py
deeptrain/util/data_loaders.py
deeptrain/util/experimental.py
deeptrain/util/logging.py
deeptrain/util/misc.py
deeptrain/util/preprocessors.py
deeptrain/util/saving.py
deeptrain/util/searching.py
deeptrain/util/training.py
deeptrain/util/fonts/__init__.py
deeptrain/util/fonts/consola.ttf
deeptrain-0.6.0.dist-info/LICENSE
deeptrain-0.6.0.dist-info/METADATA
deeptrain-0.6.0.dist-info/WHEEL
deeptrain-0.6.0.dist-info/top_level.txt
deeptrain-0.6.0.dist-info/zip-safe
deeptrain-0.6.0.dist-info/RECORD
