Metadata-Version: 2.1
Name: deeptrain
Version: 0.6.0
Summary: Full knowledge and control of the train state
Home-page: https://github.com/OverLordGoldDragon/deeptrain
Author: OverLordGoldDragon
Author-email: 16495490+OverLordGoldDragon@users.noreply.github.com
License: MIT
Keywords: tensorflow keras python deep-learning ai train-loop
Platform: UNKNOWN
Classifier: Programming Language :: Python :: 3.6
Classifier: Programming Language :: Python :: 3.7
Classifier: Programming Language :: Python :: 3.8
Classifier: License :: OSI Approved :: MIT License
Classifier: Operating System :: OS Independent
Classifier: Intended Audience :: Developers
Classifier: Intended Audience :: Education
Classifier: Intended Audience :: Information Technology
Classifier: Intended Audience :: Science/Research
Classifier: Topic :: Utilities
Classifier: Topic :: Scientific/Engineering
Classifier: Topic :: Scientific/Engineering :: Artificial Intelligence
Classifier: Topic :: Scientific/Engineering :: Information Analysis
Classifier: Topic :: Software Development
Classifier: Topic :: Software Development :: Libraries :: Python Modules
Requires-Dist: numpy
Requires-Dist: matplotlib
Requires-Dist: tensorflow
Requires-Dist: h5py
Requires-Dist: see-rnn
Provides-Extra: docs
Requires-Dist: setuptools (>=41.0.0) ; extra == 'docs'
Requires-Dist: twine (>=1.15.0) ; extra == 'docs'
Requires-Dist: Keras ; extra == 'docs'
Requires-Dist: coverage ; extra == 'docs'
Requires-Dist: pytest ; extra == 'docs'
Requires-Dist: pytest-cov ; extra == 'docs'
Requires-Dist: pycode ; extra == 'docs'
Requires-Dist: pandas ; extra == 'docs'
Requires-Dist: pillow ; extra == 'docs'
Requires-Dist: sklearn ; extra == 'docs'
Requires-Dist: py-lz4framed ; extra == 'docs'
Provides-Extra: travis
Requires-Dist: setuptools (>=41.0.0) ; extra == 'travis'
Requires-Dist: twine (>=1.15.0) ; extra == 'travis'
Requires-Dist: Keras ; extra == 'travis'
Requires-Dist: coverage ; extra == 'travis'
Requires-Dist: pytest ; extra == 'travis'
Requires-Dist: pytest-cov ; extra == 'travis'
Requires-Dist: pycode ; extra == 'travis'
Requires-Dist: pandas ; extra == 'travis'
Requires-Dist: pillow ; extra == 'travis'
Requires-Dist: sklearn ; extra == 'travis'
Requires-Dist: py-lz4framed ; extra == 'travis'
